langchain_benchmarks/.gitignore
langchain_benchmarks/__init__.py
langchain_benchmarks/extraction/__init__.py
langchain_benchmarks/extraction/evaluators.py
langchain_benchmarks/extraction/implementations.py
langchain_benchmarks/extraction/tasks/__init__.py
langchain_benchmarks/extraction/tasks/chat_extraction/__init__.py
langchain_benchmarks/extraction/tasks/chat_extraction/evaluators.py
langchain_benchmarks/extraction/tasks/chat_extraction/schema.py
langchain_benchmarks/extraction/tasks/email_task.py
langchain_benchmarks/extraction/tasks/high_cardinality/__init__.py
langchain_benchmarks/extraction/tasks/high_cardinality/name_correction.py
langchain_benchmarks/model_registration.py
langchain_benchmarks/rag/.gitignore
langchain_benchmarks/rag/__init__.py
langchain_benchmarks/rag/evaluators.py
langchain_benchmarks/rag/tasks/.gitignore
langchain_benchmarks/rag/tasks/__init__.py
langchain_benchmarks/rag/tasks/langchain_docs/README.md
langchain_benchmarks/rag/tasks/langchain_docs/__init__.py
langchain_benchmarks/rag/tasks/langchain_docs/_ingest_docs.py
langchain_benchmarks/rag/tasks/langchain_docs/architectures/__init__.py
langchain_benchmarks/rag/tasks/langchain_docs/architectures/chain_registry.py
langchain_benchmarks/rag/tasks/langchain_docs/architectures/crqa.py
langchain_benchmarks/rag/tasks/langchain_docs/indexing/.gitignore
langchain_benchmarks/rag/tasks/langchain_docs/indexing/__init__.py
langchain_benchmarks/rag/tasks/langchain_docs/indexing/retriever_registry.py
langchain_benchmarks/rag/tasks/langchain_docs/task.py
langchain_benchmarks/rag/tasks/multi_modal_slide_decks/__init__.py
langchain_benchmarks/rag/tasks/multi_modal_slide_decks/indexing/__init__.py
langchain_benchmarks/rag/tasks/multi_modal_slide_decks/indexing/retriever_registry.py
langchain_benchmarks/rag/tasks/multi_modal_slide_decks/task.py
langchain_benchmarks/rag/tasks/semi_structured_reports/__init__.py
langchain_benchmarks/rag/tasks/semi_structured_reports/indexing/.gitignore
langchain_benchmarks-0.0.14.dist-info/LICENSE
langchain_benchmarks-0.0.14.dist-info/METADATA
langchain_benchmarks-0.0.14.dist-info/WHEEL
langchain_benchmarks-0.0.14.dist-info/RECORD
