Metadata-Version: 2.1
Name: langchain-benchmarks
Version: 0.0.14
Summary: 🦜💪 Flex those feathers!
License: MIT
Author: LangChain AI
Requires-Python: >=3.8.1,<4.0.0
Classifier: License :: OSI Approved :: MIT License
Classifier: Programming Language :: Python :: 3
Classifier: Programming Language :: Python :: 3.9
Classifier: Programming Language :: Python :: 3.10
Classifier: Programming Language :: Python :: 3.11
Requires-Dist: ipywidgets (>=8,<9)
Requires-Dist: langchain (>=0.2.7,<0.3.0)
Requires-Dist: langchain-community (>=0.2,<0.3)
Requires-Dist: langchain-openai (>=0.1.14,<0.2.0)
Requires-Dist: langsmith (>=0.0.70)
Requires-Dist: tabulate (>=0.8.0)
Requires-Dist: tqdm (>=4,<5)
